app_deploy/__init__.py
app_deploy/__main__.py
test/__init__.py
test/test_init.py
test/test_main.py
lcmap_app_deploy-0.3.1.dist-info/METADATA
lcmap_app_deploy-0.3.1.dist-info/WHEEL
lcmap_app_deploy-0.3.1.dist-info/entry_points.txt
lcmap_app_deploy-0.3.1.dist-info/top_level.txt
lcmap_app_deploy-0.3.1.dist-info/RECORD
