Metadata-Version: 2.1
Name: lcmap-app-deploy
Version: 0.3.1
Summary: Backup/restore Marathon app job definitions.
Home-page: https://eroslab.cr.usgs.gov/lcmap/deployment
Author: USGS EROS LCMAP
Author-email: 
License: Unlicense
Keywords: usgs eros lcmap
Platform: UNKNOWN
Classifier: Development Status :: 3 - Alpha
Classifier: License :: Public Domain
Classifier: Programming Language :: Python :: 3.6
Requires-Python: >=3.6
Requires-Dist: cytoolz
Requires-Dist: requests
Provides-Extra: deploy
Requires-Dist: twine ; extra == 'deploy'
Provides-Extra: docs
Requires-Dist: sphinx ; extra == 'docs'
Requires-Dist: sphinx-autobuild ; extra == 'docs'
Requires-Dist: sphinx-rtd-theme ; extra == 'docs'
Provides-Extra: tests
Requires-Dist: pytest ; extra == 'tests'
Requires-Dist: pytest-cov ; extra == 'tests'
